setup.py
prince_purchase_recommender/__init__.py
prince_purchase_recommender/purchase_recommender.py
prince_purchase_recommender.egg-info/PKG-INFO
prince_purchase_recommender.egg-info/SOURCES.txt
prince_purchase_recommender.egg-info/dependency_links.txt
prince_purchase_recommender.egg-info/not-zip-safe
prince_purchase_recommender.egg-info/top_level.txt