Metadata-Version: 1.0
Name: prince-purchase-recommender
Version: 1.7
Summary: Purchase Recommendation for customer
Home-page: UNKNOWN
Author: Prince Singh Bhadauria
Author-email: princesinghbhadauria@gmail.com
License: UNKNOWN
Platform: UNKNOWN
